<?xml version="1.0" encoding="UTF-8"?><!-- This file is used for the conversion and normalisation of Europeana source files -->
<profiles inputDirectory="/var/sourcedata/xml/" outputDirectory="/var/destinationdata/">
    <profile name="03907_Ag_FR_MCC_archim" directory="03907_Ag_FR_MCC_archim/input_source/" publisherId="039">
        <sources>
            <source file="03907_Ag_FR_MCC_archim.xml"
                    recordSeparator="NOTICE"
                    collectionId="03907">
                <additions>
                    <addition key="EUROPEANA_COUNTRY" value="france_t"/>
                    <addition key="EUROPEANA_PROVIDER" value="Archim"/>
                    <addition key="EUROPEANA_TYPE" value="IMAGE"/>
                    <addition key="EUROPEANA_LANGUAGE" value="fr"/>
                </additions>
                <field-mappings>
                    <field-mapping from="/BASE/DOMAINE"/>
                    <field-mapping from="/BASE/NAME"/>
                    <field-mapping from="/BASE/NOTICES/NOTICE/ACCESSIB"/>
                    <field-mapping from="/BASE/NOTICES/NOTICE/ANALYSE">
                        <to key="DC_TITLE"/>
                    </field-mapping>
                    <field-mapping from="/BASE/NOTICES/NOTICE/CODEVISU"/>
                    <field-mapping from="/BASE/NOTICES/NOTICE/CODVALID"/>
                    <field-mapping from="/BASE/NOTICES/NOTICE/COTE">
                        <to key="DC_IDENTIFIER"/>
                    </field-mapping>
                    <field-mapping from="/BASE/NOTICES/NOTICE/COTORIGI"/>
                    <field-mapping from="/BASE/NOTICES/NOTICE/COULEUR"/>
                    <field-mapping from="/BASE/NOTICES/NOTICE/DATDEB">
                        <to converter="YearExtractor" key="EUROPEANA_YEAR"/>
                        <to key="DC_DATE"/>
                    </field-mapping>
                    <field-mapping from="/BASE/NOTICES/NOTICE/DATFI">
                        <to key="DC_DATE"/>
                    </field-mapping>
                    <!-- decision requested on the interpretation of range of dates between DATDEB and DATFI -->
                    <field-mapping from="/BASE/NOTICES/NOTICE/DATMAJ"/>
                    <field-mapping from="/BASE/NOTICES/NOTICE/DATSAISI"/>
                    <field-mapping from="/BASE/NOTICES/NOTICE/DOMAINE">
                        <to key="EUROPEANA_UNSTORED"/>
                    </field-mapping>
                    <field-mapping from="/BASE/NOTICES/NOTICE/DOSSIER">
                        <to key="EUROPEANA_UNSTORED"/>
                    </field-mapping>
                    <field-mapping from="/BASE/NOTICES/NOTICE/FDSORIGI"/>
                    <field-mapping from="/BASE/NOTICES/NOTICE/FONDS"/>
                    <field-mapping from="/BASE/NOTICES/NOTICE/FORME">
                        <to key="EUROPEANA_UNSTORED"/>
                    </field-mapping>
                    <field-mapping from="/BASE/NOTICES/NOTICE/IDPROD"/>
                    <field-mapping from="/BASE/NOTICES/NOTICE/IMG"/>
                    <field-mapping from="/BASE/NOTICES/NOTICE/LBASE"/>
                    <field-mapping from="/BASE/NOTICES/NOTICE/LIEUX">
                        <to key="DCTERMS_SPATIAL"/>
                    </field-mapping>
                    <field-mapping from="/BASE/NOTICES/NOTICE/MOSA"/>
                    <field-mapping from="/BASE/NOTICES/NOTICE/MOTS-MAT">
                        <to key="DC_SUBJECT"/>
                    </field-mapping>
                    <field-mapping from="/BASE/NOTICES/NOTICE/NOIMAGE"/>
                    <field-mapping from="/BASE/NOTICES/NOTICE/NOMDOS">
                        <to key="EUROPEANA_UNSTORED"/>
                    </field-mapping>
                    <field-mapping from="/BASE/NOTICES/NOTICE/NOTES">
                        <to key="EUROPEANA_UNSTORED"/>
                    </field-mapping>
                    <field-mapping from="/BASE/NOTICES/NOTICE/NUMF"/>
                    <field-mapping from="/BASE/NOTICES/NOTICE/NUMP"/>
                    <field-mapping from="/BASE/NOTICES/NOTICE/NUMPHOTO"/>
                    <field-mapping from="/BASE/NOTICES/NOTICE/NUMSP"/>
                    <field-mapping from="/BASE/NOTICES/NOTICE/PERSONNE">
                        <to key="DC_CONTRIBUTOR"/>
                    </field-mapping>
                    <field-mapping from="/BASE/NOTICES/NOTICE/PIECEACT"/>
                    <field-mapping from="/BASE/NOTICES/NOTICE/REDACT"/>
                    <field-mapping from="/BASE/NOTICES/NOTICE/REF"/>
                    <field-mapping from="/BASE/NOTICES/NOTICE/REFIM"/>
                    <field-mapping from="/BASE/NOTICES/NOTICE/REPRODUC"/>
                    <field-mapping from="/BASE/NOTICES/NOTICE/SS-SERIE">
                        <to key="EUROPEANA_UNSTORED"/>
                    </field-mapping>
                    <field-mapping from="/BASE/NOTICES/NOTICE/SUPPORT">
                        <to key="DCTERMS_MEDIUM"/>
                    </field-mapping>
                    <field-mapping from="/BASE/NOTICES/NOTICE/TAILLE">
                        <to key="DCTERMS_EXTENT"/>
                    </field-mapping>
                    <field-mapping from="/BASE/NOTICES/NOTICE/TECHNIQ">
                        <to key="EUROPEANA_UNSTORED"/>
                    </field-mapping>
                    <field-mapping from="/BASE/NOTICES/NOTICE/TYPEDOC">
                        <to key="EUROPEANA_UNSTORED"/>
                    </field-mapping>
                    <!-- create for all the europeana:type with the value"image"  -->
                    <field-mapping from="/BASE/NOTICES/NOTICE/TYPSP"/>
                    <field-mapping from="/BASE/NOTICES/NOTICE/VIDEO">
                        <!--<to converter="Delimiter|;"/>-->
                        <to converter="PrefixSuffixFirstDelimited|http://www.culture.gouv.fr| |;"
                            key="EUROPEANA_OBJECT"/>
                        <to converter="PrefixSuffixFirstDelimited|http://www.culture.gouv.fr| |;"
                            key="EUROPEANA_IS_SHOWN_BY"/>
                    </field-mapping>
                    <!-- take the second value after the";" and prefix it with 'http://www.culture.gouv.fr' #take the first value berfore the";" and prefix it with 'http://www.culture.gouv.fr' -->
                    <field-mapping from="/BASE/NOTICES/NOTICE@ID">
                        <to converter="PrefixSuffix|http://www.culture.gouv.fr/public/mistral/caran_fr?ACTION=CHERCHER&amp;FIELD_1=REF&amp;VALUE_1=| "
                            key="EUROPEANA_IS_SHOWN_AT"/>
                        <to uriMapping="true" key="EUROPEANA_URI"/>
                    </field-mapping>
                    <!-- create the link by prefixing the value with 'http://www.culture.gouv.fr/public/mistral/caran_fr?ACTION=CHERCHER&FIELD_1=REF&VALUE_1=' -->
                    <!-- create europeana:source in each record with the value: 'Centre historique des Archives nationales' -->
                </field-mappings>
            </source>
        </sources>
        <type-mappings>
            <type-mapping type="TEXT">
                <from>text</from>
            </type-mapping>
        </type-mappings>
    </profile>
    <profile name="900_L_AT_NatLib_Bildarchiv_tel_onbba" directory="900_L_AT_NatLib_Bildarchiv_tel_onbba/input_source/" publisherId="900">
        <sources>
            <source file="900_L_AT_NatLib_Bildarchiv_tel_onbba.xml"
                    recordSeparator="{http://oai-onb-dev-ext.gideon.at/OAI/tel_onbba/}tel_onbba"
                    collectionId="900">
                <additions>
                    <addition key="EUROPEANA_LANGUAGE" value="de"/>
                    <addition key="EUROPEANA_COUNTRY" value="austria_t"/>
                    <addition key="EUROPEANA_PROVIDER" value="ÖNB"/>
                </additions>
                <field-mappings>
                    <field-mapping from="/harvest/OAI-PMH/Identify/adminEmail"/>
                    <field-mapping from="/harvest/OAI-PMH/Identify/baseURL"/>
                    <field-mapping from="/harvest/OAI-PMH/Identify/deletedRecord"/>
                    <field-mapping from="/harvest/OAI-PMH/Identify/description/oai-identifier/delimiter"/>
                    <field-mapping from="/harvest/OAI-PMH/Identify/description/oai-identifier/repositoryIdentifier"/>
                    <field-mapping from="/harvest/OAI-PMH/Identify/description/oai-identifier/sampleIdentifier"/>
                    <field-mapping from="/harvest/OAI-PMH/Identify/description/oai-identifier/scheme"/>
                    <field-mapping from="/harvest/OAI-PMH/Identify/description/oai-identifier@xsi:schemaLocation"/>
                    <field-mapping from="/harvest/OAI-PMH/Identify/earliestDatestamp"/>
                    <field-mapping from="/harvest/OAI-PMH/Identify/granularity"/>
                    <field-mapping from="/harvest/OAI-PMH/Identify/protocolVersion"/>
                    <field-mapping from="/harvest/OAI-PMH/Identify/repositoryName"/>
                    <field-mapping from="/harvest/OAI-PMH/ListMetadataFormats/metadataFormat/metadataNamespace"/>
                    <field-mapping from="/harvest/OAI-PMH/ListMetadataFormats/metadataFormat/metadataPrefix"/>
                    <field-mapping from="/harvest/OAI-PMH/ListMetadataFormats/metadataFormat/schema"/>
                    <field-mapping from="/harvest/OAI-PMH/ListRecords/record/header/datestamp"/>
                    <field-mapping from="/harvest/OAI-PMH/ListRecords/record/header/identifier">
                        <to key="DC_IDENTIFIER"/>
                    </field-mapping>
                    <field-mapping from="/harvest/OAI-PMH/ListRecords/record/header/setSpec"/>
                    <field-mapping from="/harvest/OAI-PMH/ListRecords/record/metadata/tel_onbba:tel_onbba/dc:creator">
                        <to key="DC_CREATOR"/>
                    </field-mapping>
                    <field-mapping from="/harvest/OAI-PMH/ListRecords/record/metadata/tel_onbba:tel_onbba/dc:date">
                        <to converter="YearExtractor" key="EUROPEANA_YEAR"/>
                        <to key="DC_DATE"/>
                    </field-mapping>
                    <field-mapping
                            from="/harvest/OAI-PMH/ListRecords/record/metadata/tel_onbba:tel_onbba/dc:description">
                        <to key="DC_DESCRIPTION"/>
                    </field-mapping>
                    <field-mapping
                            from="/harvest/OAI-PMH/ListRecords/record/metadata/tel_onbba:tel_onbba/dc:description@xml:lang"/>
                    <field-mapping from="/harvest/OAI-PMH/ListRecords/record/metadata/tel_onbba:tel_onbba/dc:identifier"
                                   chooseFirst="true">
                        <to key="EUROPEANA_IS_SHOWN_BY"/>
                        <to key="EUROPEANA_OBJECT"/>
                    </field-mapping>
                    <field-mapping from="/harvest/OAI-PMH/ListRecords/record/metadata/tel_onbba:tel_onbba/dc:rights">
                        <to key="DC_RIGHTS"/>
                    </field-mapping>
                    <field-mapping from="/harvest/OAI-PMH/ListRecords/record/metadata/tel_onbba:tel_onbba/dc:subject">
                        <to key="DC_SUBJECT"/>
                    </field-mapping>
                    <field-mapping from="/harvest/OAI-PMH/ListRecords/record/metadata/tel_onbba:tel_onbba/dc:title">
                        <to key="DC_TITLE"/>
                    </field-mapping>
                    <field-mapping
                            from="/harvest/OAI-PMH/ListRecords/record/metadata/tel_onbba:tel_onbba/dc:title@xml:lang"/>
                    <field-mapping from="/harvest/OAI-PMH/ListRecords/record/metadata/tel_onbba:tel_onbba/dc:type">
                        <to typeMapping="true" key="EUROPEANA_TYPE"/>
                    </field-mapping>
                    <field-mapping
                            from="/harvest/OAI-PMH/ListRecords/record/metadata/tel_onbba:tel_onbba/dcterms:hasFormat">
                        <to key="DCTERMS_HAS_FORMAT"/>
                    </field-mapping>
                    <field-mapping
                            from="/harvest/OAI-PMH/ListRecords/record/metadata/tel_onbba:tel_onbba/dcterms:temporal">
                        <to key="DCTERMS_TEMPORAL"/>
                    </field-mapping>
                    <field-mapping
                            from="/harvest/OAI-PMH/ListRecords/record/metadata/tel_onbba:tel_onbba/onbba:caption">
                        <to key="DC_DESCRIPTION"/>
                    </field-mapping>
                    <field-mapping
                            from="/harvest/OAI-PMH/ListRecords/record/metadata/tel_onbba:tel_onbba/onbba:caption@language">
                        <to key="EUROPEANA_UNSTORED"/>
                    </field-mapping>
                    <field-mapping
                            from="/harvest/OAI-PMH/ListRecords/record/metadata/tel_onbba:tel_onbba/onbba:caption@type">
                        <to key="EUROPEANA_UNSTORED"/>
                    </field-mapping>
                    <field-mapping
                            from="/harvest/OAI-PMH/ListRecords/record/metadata/tel_onbba:tel_onbba/onbba:dateAfter">
                        <to key="DC_DATE"/>
                    </field-mapping>
                    <field-mapping
                            from="/harvest/OAI-PMH/ListRecords/record/metadata/tel_onbba:tel_onbba/onbba:dateBefore">
                        <to key="DC_DATE"/>
                    </field-mapping>
                    <field-mapping
                            from="/harvest/OAI-PMH/ListRecords/record/metadata/tel_onbba:tel_onbba/onbba:dimensions">
                        <to key="DCTERMS_EXTENT"/>
                    </field-mapping>
                    <field-mapping from="/harvest/OAI-PMH/ListRecords/record/metadata/tel_onbba:tel_onbba/onbba:event">
                        <to key="EUROPEANA_UNSTORED"/>
                    </field-mapping>
                    <field-mapping
                            from="/harvest/OAI-PMH/ListRecords/record/metadata/tel_onbba:tel_onbba/onbba:event@beginDate">
                        <to key="DC_DATE"/>
                    </field-mapping>
                    <field-mapping
                            from="/harvest/OAI-PMH/ListRecords/record/metadata/tel_onbba:tel_onbba/onbba:event@description">
                        <to key="EUROPEANA_UNSTORED"/>
                    </field-mapping>
                    <field-mapping
                            from="/harvest/OAI-PMH/ListRecords/record/metadata/tel_onbba:tel_onbba/onbba:event@endDate">
                        <to key="DC_DATE"/>
                    </field-mapping>
                    <field-mapping
                            from="/harvest/OAI-PMH/ListRecords/record/metadata/tel_onbba:tel_onbba/onbba:event@from">
                        <to key="EUROPEANA_UNSTORED"/>
                    </field-mapping>
                    <field-mapping
                            from="/harvest/OAI-PMH/ListRecords/record/metadata/tel_onbba:tel_onbba/onbba:imageType">
                        <to key="EUROPEANA_UNSTORED"/>
                    </field-mapping>
                    <field-mapping
                            from="/harvest/OAI-PMH/ListRecords/record/metadata/tel_onbba:tel_onbba/onbba:ownerCollectionID"/>
                    <field-mapping
                            from="/harvest/OAI-PMH/ListRecords/record/metadata/tel_onbba:tel_onbba/onbba:ownerInstitution">
                        <to key="EUROPEANA_UNSTORED"/>
                    </field-mapping>
                    <field-mapping
                            from="/harvest/OAI-PMH/ListRecords/record/metadata/tel_onbba:tel_onbba/onbba:ownerInstitutionID"/>
                    <field-mapping
                            from="/harvest/OAI-PMH/ListRecords/record/metadata/tel_onbba:tel_onbba/onbba:personDepicted">
                        <to key="DC_COVERAGE"/>
                    </field-mapping>
                    <field-mapping
                            from="/harvest/OAI-PMH/ListRecords/record/metadata/tel_onbba:tel_onbba/onbba:placeDepicted">
                        <to key="DCTERMS_SPATIAL"/>
                    </field-mapping>
                    <field-mapping
                            from="/harvest/OAI-PMH/ListRecords/record/metadata/tel_onbba:tel_onbba/onbba:placeDepicted@country">
                        <to key="DCTERMS_SPATIAL"/>
                    </field-mapping>
                    <field-mapping
                            from="/harvest/OAI-PMH/ListRecords/record/metadata/tel_onbba:tel_onbba/onbba:placeDepicted@region">
                        <to key="DCTERMS_SPATIAL"/>
                    </field-mapping>
                    <field-mapping
                            from="/harvest/OAI-PMH/ListRecords/record/metadata/tel_onbba:tel_onbba/onbba:technique">
                        <to key="EUROPEANA_UNSTORED"/>
                    </field-mapping>
                    <field-mapping from="/harvest/OAI-PMH/ListRecords/record/metadata/tel_onbba:tel_onbba/onbba:view">
                        <to key="EUROPEANA_UNSTORED"/>
                    </field-mapping>
                    <field-mapping from="/harvest/OAI-PMH/ListRecords/record/metadata/tel_onbba:tel_onbba/tel:recordId">
                        <to key="EUROPEANA_IS_SHOWN_AT"/>
                        <to uriMapping="true" key="EUROPEANA_URI"/>
                    </field-mapping>
                    <field-mapping
                            from="/harvest/OAI-PMH/ListRecords/record/metadata/tel_onbba:tel_onbba/tel:recordId@xsi:type"/>
                    <field-mapping
                            from="/harvest/OAI-PMH/ListRecords/record/metadata/tel_onbba:tel_onbba/tel:thumbnail"/>
                    <field-mapping
                            from="/harvest/OAI-PMH/ListRecords/record/metadata/tel_onbba:tel_onbba/tel:thumbnail@xsi:type"/>
                    <field-mapping
                            from="/harvest/OAI-PMH/ListRecords/record/metadata/tel_onbba:tel_onbba@xsi:schemaLocation"/>
                    <field-mapping from="/harvest/OAI-PMH/ListRecords/resumptionToken"/>
                    <field-mapping from="/harvest/OAI-PMH/ListRecords/resumptionToken@completeListSize"/>
                    <field-mapping from="/harvest/OAI-PMH/ListSets/set/setName"/>
                    <field-mapping from="/harvest/OAI-PMH/ListSets/set/setSpec"/>
                    <field-mapping from="/harvest/OAI-PMH/request"/>
                    <field-mapping from="/harvest/OAI-PMH/request@metadataPrefix"/>
                    <field-mapping from="/harvest/OAI-PMH/request@resumptionToken"/>
                    <field-mapping from="/harvest/OAI-PMH/request@set"/>
                    <field-mapping from="/harvest/OAI-PMH/request@verb"/>
                    <field-mapping from="/harvest/OAI-PMH/responseDate"/>
                    <field-mapping from="/harvest/OAI-PMH@xsi:schemaLocation"/>
                </field-mappings>
            </source>
        </sources>
        <type-mappings>
            <type-mapping type="IMAGE">
                <from>Fotografie</from>
                <from>Druckgraphik</from>
                <from>Zeichnung</from>
                <from>Malerei</from>
            </type-mapping>
        </type-mappings>
    </profile>
    <profile name="04701_M_DE_Digicult_museumdat" directory="04701_M_DE_Digicult_museumdat/input_source/" publisherId="047">
        <sources>
            <source file="04701_M_DE_Digicult_museumdat.xml"
                    recordSeparator="{http://museum.zib.de/museumdat}museumdat"
                    collectionId="04701">
                <additions>
                    <addition key="EUROPEANA_COUNTRY" value="germany_t"/>
                    <addition key="EUROPEANA_PROVIDER" value="Digicult"/>
                    <addition key="EUROPEANA_TYPE" value="IMAGE"/>
                    <addition key="EUROPEANA_LANGUAGE" value="de"/>
                </additions>
                <field-mappings>
                    <field-mapping
                            from="/museumdat:museumdatWrap/museumdat:museumdat/museumdat:administrativeMetadata/museumdat:recordWrap/museumdat:recordID">
                        <to key="DC_IDENTIFIER"/>
                    </field-mapping>
                    <field-mapping
                            from="/museumdat:museumdatWrap/museumdat:museumdat/museumdat:administrativeMetadata/museumdat:recordWrap/museumdat:recordInfoSet/museumdat:recordInfoLink">
                        <to key="EUROPEANA_IS_SHOWN_AT"/>
                    </field-mapping>
                    <field-mapping
                            from="/museumdat:museumdatWrap/museumdat:museumdat/museumdat:administrativeMetadata/museumdat:recordWrap/museumdat:recordInfoSet/museumdat:recordMetadataDate"/>
                    <!--  dc:source candidate -->
                    <field-mapping
                            from="/museumdat:museumdatWrap/museumdat:museumdat/museumdat:administrativeMetadata/museumdat:recordWrap/museumdat:recordSource">
                        <to key="EUROPEANA_UNSTORED"/>
                    </field-mapping>
                    <field-mapping
                            from="/museumdat:museumdatWrap/museumdat:museumdat/museumdat:administrativeMetadata/museumdat:resourceWrap/museumdat:resourceSet/museumdat:linkResource"
                            filter="museumdat:type=image_overview">
                        <to key="EUROPEANA_IS_SHOWN_BY"/>
                        <to key="EUROPEANA_OBJECT"/>
                    </field-mapping>
                    <field-mapping
                            from="/museumdat:museumdatWrap/museumdat:museumdat/museumdat:administrativeMetadata/museumdat:resourceWrap/museumdat:resourceSet/museumdat:linkResource@museumdat:formatResource">
                        <to key="DC_FORMAT"/>
                    </field-mapping>
                    <field-mapping
                            from="/museumdat:museumdatWrap/museumdat:museumdat/museumdat:administrativeMetadata/museumdat:resourceWrap/museumdat:resourceSet/museumdat:linkResource@museumdat:type"/>
                    <field-mapping
                            from="/museumdat:museumdatWrap/museumdat:museumdat/museumdat:administrativeMetadata/museumdat:rightsWork">
                        <to key="DC_RIGHTS"/>
                    </field-mapping>
                    <field-mapping
                            from="/museumdat:museumdatWrap/museumdat:museumdat/museumdat:descriptiveMetadata/museumdat:descriptionWrap/museumdat:descriptiveNoteWrap/museumdat:descriptiveNoteSet/museumdat:descriptiveNote">
                        <to key="DC_DESCRIPTION"/>
                    </field-mapping>
                    <field-mapping
                            from="/museumdat:museumdatWrap/museumdat:museumdat/museumdat:descriptiveMetadata/museumdat:descriptionWrap/museumdat:descriptiveNoteWrap/museumdat:descriptiveNoteSet@museumdat:type"/>
                    <field-mapping
                            from="/museumdat:museumdatWrap/museumdat:museumdat/museumdat:descriptiveMetadata/museumdat:descriptionWrap/museumdat:displayCreationDate">
                        <to key="DCTERMS_CREATED"/>
                        <to convertor="YearExtract" key="EUROPEANA_YEAR"/>
                    </field-mapping>
                    <field-mapping
                            from="/museumdat:museumdatWrap/museumdat:museumdat/museumdat:descriptiveMetadata/museumdat:descriptionWrap/museumdat:displayMeasurements">
                        <to key="DCTERMS_EXTENT"/>
                    </field-mapping>
                    <field-mapping
                            from="/museumdat:museumdatWrap/museumdat:museumdat/museumdat:descriptiveMetadata/museumdat:eventWrap/museumdat:indexingEventWrap/museumdat:indexingEventSet/museumdat:eventType">
                        <to key="EUROPEANA_UNSTORED"/>
                    </field-mapping>
                    <field-mapping
                            from="/museumdat:museumdatWrap/museumdat:museumdat/museumdat:descriptiveMetadata/museumdat:eventWrap/museumdat:indexingEventWrap/museumdat:indexingEventSet/museumdat:indexingActorSet/museumdat:extentActor">
                        <to key="EUROPEANA_UNSTORED"/>
                    </field-mapping>
                    <field-mapping
                            from="/museumdat:museumdatWrap/museumdat:museumdat/museumdat:descriptiveMetadata/museumdat:eventWrap/museumdat:indexingEventWrap/museumdat:indexingEventSet/museumdat:indexingActorSet/museumdat:nameActorSet/museumdat:nameActor">
                        <to key="DC_CREATOR"/>
                        <to key="DC_CONTRIBUTOR"/>
                    </field-mapping>
                    <field-mapping
                            from="/museumdat:museumdatWrap/museumdat:museumdat/museumdat:descriptiveMetadata/museumdat:eventWrap/museumdat:indexingEventWrap/museumdat:indexingEventSet/museumdat:indexingActorSet/museumdat:nameActorSet/museumdat:nameActor@museumdat:termsource"/>
                    <field-mapping
                            from="/museumdat:museumdatWrap/museumdat:museumdat/museumdat:descriptiveMetadata/museumdat:eventWrap/museumdat:indexingEventWrap/museumdat:indexingEventSet/museumdat:indexingActorSet/museumdat:nameActorSet/museumdat:nameActor@museumdat:termsourceID"/>
                    <field-mapping
                            from="/museumdat:museumdatWrap/museumdat:museumdat/museumdat:descriptiveMetadata/museumdat:eventWrap/museumdat:indexingEventWrap/museumdat:indexingEventSet/museumdat:indexingActorSet/museumdat:roleActor">
                        <to key="EUROPEANA_UNSTORED"/>
                    </field-mapping>
                    <!--  (YEAR) candidate (see latestDate) -->
                    <field-mapping
                            from="/museumdat:museumdatWrap/museumdat:museumdat/museumdat:descriptiveMetadata/museumdat:eventWrap/museumdat:indexingEventWrap/museumdat:indexingEventSet/museumdat:indexingDates/museumdat:earliestDate">
                        <to key="DC_DATE"/>
                    </field-mapping>
                    <!--  (YEAR) candidate (see earliestDate) -->
                    <field-mapping
                            from="/museumdat:museumdatWrap/museumdat:museumdat/museumdat:descriptiveMetadata/museumdat:eventWrap/museumdat:indexingEventWrap/museumdat:indexingEventSet/museumdat:indexingDates/museumdat:latestDate">
                        <to key="DC_DATE"/>
                    </field-mapping>
                    <field-mapping
                            from="/museumdat:museumdatWrap/museumdat:museumdat/museumdat:descriptiveMetadata/museumdat:eventWrap/museumdat:indexingEventWrap/museumdat:indexingEventSet/museumdat:indexingLocationWrap/museumdat:indexingLocationSet/museumdat:nameLocationSet/museumdat:nameLocation">
                        <to key="EUROPEANA_UNSTORED"/>
                    </field-mapping>
                    <field-mapping
                            from="/museumdat:museumdatWrap/museumdat:museumdat/museumdat:descriptiveMetadata/museumdat:eventWrap/museumdat:indexingEventWrap/museumdat:indexingEventSet/museumdat:indexingLocationWrap/museumdat:indexingLocationSet/museumdat:nameLocationSet/museumdat:nameLocation@museumdat:imported"/>
                    <field-mapping
                            from="/museumdat:museumdatWrap/museumdat:museumdat/museumdat:descriptiveMetadata/museumdat:eventWrap/museumdat:indexingEventWrap/museumdat:indexingEventSet/museumdat:indexingLocationWrap/museumdat:indexingLocationSet/museumdat:nameLocationSet/museumdat:nameLocation@museumdat:termsource"/>
                    <field-mapping
                            from="/museumdat:museumdatWrap/museumdat:museumdat/museumdat:descriptiveMetadata/museumdat:eventWrap/museumdat:indexingEventWrap/museumdat:indexingEventSet/museumdat:indexingLocationWrap/museumdat:indexingLocationSet/museumdat:nameLocationSet/museumdat:nameLocation@museumdat:termsourceID"/>
                    <field-mapping
                            from="/museumdat:museumdatWrap/museumdat:museumdat/museumdat:descriptiveMetadata/museumdat:eventWrap/museumdat:indexingMaterialsTechWrap/museumdat:indexingMaterialsTechSet/museumdat:termMaterialsTech">
                        <to key="EUROPEANA_UNSTORED"/>
                    </field-mapping>
                    <field-mapping
                            from="/museumdat:museumdatWrap/museumdat:museumdat/museumdat:descriptiveMetadata/museumdat:eventWrap/museumdat:indexingMaterialsTechWrap/museumdat:indexingMaterialsTechSet/museumdat:termMaterialsTech@museumdat:imported"/>
                    <field-mapping
                            from="/museumdat:museumdatWrap/museumdat:museumdat/museumdat:descriptiveMetadata/museumdat:eventWrap/museumdat:indexingMaterialsTechWrap/museumdat:indexingMaterialsTechSet/museumdat:termMaterialsTech@museumdat:termsource"/>
                    <field-mapping
                            from="/museumdat:museumdatWrap/museumdat:museumdat/museumdat:descriptiveMetadata/museumdat:eventWrap/museumdat:indexingMaterialsTechWrap/museumdat:indexingMaterialsTechSet/museumdat:termMaterialsTech@museumdat:termsourceID"/>
                    <field-mapping
                            from="/museumdat:museumdatWrap/museumdat:museumdat/museumdat:descriptiveMetadata/museumdat:eventWrap/museumdat:indexingMaterialsTechWrap/museumdat:indexingMaterialsTechSet@museumdat:type"/>
                    <field-mapping
                            from="/museumdat:museumdatWrap/museumdat:museumdat/museumdat:descriptiveMetadata/museumdat:eventWrap/museumdat:styleWrap/museumdat:style">
                        <to key="DC_SUBJECT"/>
                    </field-mapping>
                    <field-mapping
                            from="/museumdat:museumdatWrap/museumdat:museumdat/museumdat:descriptiveMetadata/museumdat:eventWrap/museumdat:styleWrap/museumdat:style@museumdat:imported"/>
                    <field-mapping
                            from="/museumdat:museumdatWrap/museumdat:museumdat/museumdat:descriptiveMetadata/museumdat:eventWrap/museumdat:styleWrap/museumdat:style@museumdat:termsource"/>
                    <field-mapping
                            from="/museumdat:museumdatWrap/museumdat:museumdat/museumdat:descriptiveMetadata/museumdat:eventWrap/museumdat:styleWrap/museumdat:style@museumdat:termsourceID"/>
                    <!--  dc:source candidate -->
                    <field-mapping
                            from="/museumdat:museumdatWrap/museumdat:museumdat/museumdat:descriptiveMetadata/museumdat:identificationWrap/museumdat:repositoryWrap/museumdat:repositorySet/museumdat:repositoryName">
                        <to key="EUROPEANA_UNSTORED"/>
                    </field-mapping>
                    <field-mapping
                            from="/museumdat:museumdatWrap/museumdat:museumdat/museumdat:descriptiveMetadata/museumdat:identificationWrap/museumdat:repositoryWrap/museumdat:repositorySet/museumdat:workID">
                        <to key="DC_IDENTIFIER"/>
                    </field-mapping>
                    <field-mapping
                            from="/museumdat:museumdatWrap/museumdat:museumdat/museumdat:descriptiveMetadata/museumdat:identificationWrap/museumdat:repositoryWrap/museumdat:repositorySet/museumdat:workID@museumdat:type"/>
                    <field-mapping
                            from="/museumdat:museumdatWrap/museumdat:museumdat/museumdat:descriptiveMetadata/museumdat:identificationWrap/museumdat:titleWrap/museumdat:titleSet/museumdat:title">
                        <to key="DC_TITLE"/>
                    </field-mapping>
                    <field-mapping
                            from="/museumdat:museumdatWrap/museumdat:museumdat/museumdat:descriptiveMetadata/museumdat:objectClassificationWrap/museumdat:classificationWrap/museumdat:classification">
                        <to key="EUROPEANA_UNSTORED"/>
                    </field-mapping>
                    <field-mapping
                            from="/museumdat:museumdatWrap/museumdat:museumdat/museumdat:descriptiveMetadata/museumdat:objectClassificationWrap/museumdat:classificationWrap/museumdat:classification@museumdat:imported"/>
                    <field-mapping
                            from="/museumdat:museumdatWrap/museumdat:museumdat/museumdat:descriptiveMetadata/museumdat:objectClassificationWrap/museumdat:classificationWrap/museumdat:classification@museumdat:termsource"/>
                    <field-mapping
                            from="/museumdat:museumdatWrap/museumdat:museumdat/museumdat:descriptiveMetadata/museumdat:objectClassificationWrap/museumdat:classificationWrap/museumdat:classification@museumdat:termsourceID"/>
                    <field-mapping
                            from="/museumdat:museumdatWrap/museumdat:museumdat/museumdat:descriptiveMetadata/museumdat:objectClassificationWrap/museumdat:objectWorkTypeWrap/museumdat:objectWorkType">
                        <to key="EUROPEANA_UNSTORED"/>
                    </field-mapping>
                    <field-mapping
                            from="/museumdat:museumdatWrap/museumdat:museumdat/museumdat:descriptiveMetadata/museumdat:relationWrap/museumdat:indexingSubjectWrap/museumdat:indexingSubjectSet/museumdat:subjectTerm">
                        <to key="DC_SUBJECT"/>
                        <to key="DC_RELATION"/>
                    </field-mapping>
                    <field-mapping
                            from="/museumdat:museumdatWrap/museumdat:museumdat/museumdat:descriptiveMetadata/museumdat:relationWrap/museumdat:indexingSubjectWrap/museumdat:indexingSubjectSet/museumdat:subjectTerm@museumdat:encodinganalog"/>
                    <field-mapping
                            from="/museumdat:museumdatWrap/museumdat:museumdat/museumdat:descriptiveMetadata/museumdat:relationWrap/museumdat:indexingSubjectWrap/museumdat:indexingSubjectSet/museumdat:subjectTerm@museumdat:imported"/>
                    <field-mapping
                            from="/museumdat:museumdatWrap/museumdat:museumdat/museumdat:descriptiveMetadata/museumdat:relationWrap/museumdat:indexingSubjectWrap/museumdat:indexingSubjectSet/museumdat:subjectTerm@museumdat:termsource"/>
                    <field-mapping
                            from="/museumdat:museumdatWrap/museumdat:museumdat/museumdat:descriptiveMetadata/museumdat:relationWrap/museumdat:indexingSubjectWrap/museumdat:indexingSubjectSet/museumdat:subjectTerm@museumdat:termsourceID"/>
                    <field-mapping from="/museumdat:museumdatWrap@xsi:schemaLocation"/>
                </field-mappings>
            </source>
        </sources>
        <type-mappings>
            <type-mapping type="TEXT">
                <from>text</from>
            </type-mapping>
        </type-mappings>
    </profile>
    <profile name="03501_L_FR_NatLib_gallica_dc" directory="03501_L_FR_NatLib_gallica_dc/input_source/" publisherId="035">
        <sources>
            <source file="03501_L_FR_NatLib_gallica_dc.xml"
                    recordSeperator="{http://www.openarchives.org/OAI/2.0/}record"
                    collectionId="03501">
                <additions>
                    <addition key="EUROPEANA_PROVIDER" value="BNF"/>
                    <addition key="EUROPEANA_COUNTRY" value="france_t"/>
                </additions>
                <field-mappings>
                    <field-mapping from="/harvest/OAI-PMH/ListRecords/record/header/datestamp"/>
                    <field-mapping from="/harvest/OAI-PMH/ListRecords/record/header/identifier"/>
                    <field-mapping from="/harvest/OAI-PMH/ListRecords/record/header/setSpec"/>
                    <field-mapping from="/harvest/OAI-PMH/ListRecords/record/metadata/oai_dc:dc/dc:contributor">
                        <to key="DC_CONTRIBUTOR"/>
                    </field-mapping>
                    <field-mapping from="/harvest/OAI-PMH/ListRecords/record/metadata/oai_dc:dc/dc:coverage">
                        <to key="DCTERMS_SPATIAL"/>
                    </field-mapping>
                    <field-mapping from="/harvest/OAI-PMH/ListRecords/record/metadata/oai_dc:dc/dc:creator">
                        <to key="DC_CREATOR"/>
                    </field-mapping>
                    <field-mapping from="/harvest/OAI-PMH/ListRecords/record/metadata/oai_dc:dc/dc:date">
                        <to converter="ExtractYear" key="EUROPEANA_YEAR"/>
                        <to key="DC_DATE"/>
                    </field-mapping>
                    <field-mapping from="/harvest/OAI-PMH/ListRecords/record/metadata/oai_dc:dc/dc:description">
                        <to key="DC_DESCRIPTION"/>
                    </field-mapping>
                    <field-mapping from="/harvest/OAI-PMH/ListRecords/record/metadata/oai_dc:dc/dc:format">
                        <to key="DC_FORMAT"/>
                    </field-mapping>
                    <field-mapping from="/harvest/OAI-PMH/ListRecords/record/metadata/oai_dc:dc/dc:identifier">
                        <to key="EUROPEANA_IS_SHOWN_BY"/>
                        <to uriMapping="true" key="EUROPEANA_URI"/>
                    </field-mapping>
                    <field-mapping from="/harvest/OAI-PMH/ListRecords/record/metadata/oai_dc:dc/dc:language">
                        <to key="DC_LANGUAGE"/>
                    </field-mapping>
                    <field-mapping from="/harvest/OAI-PMH/ListRecords/record/metadata/oai_dc:dc/dc:publisher">
                        <to key="DC_PUBLISHER"/>
                    </field-mapping>
                    <field-mapping from="/harvest/OAI-PMH/ListRecords/record/metadata/oai_dc:dc/dc:relation">
                        <to key="DC_RELATION"/>
                    </field-mapping>
                    <field-mapping from="/harvest/OAI-PMH/ListRecords/record/metadata/oai_dc:dc/dc:rights">
                        <to key="DC_RIGHTS"/>
                    </field-mapping>
                    <field-mapping from="/harvest/OAI-PMH/ListRecords/record/metadata/oai_dc:dc/dc:rights@xml:lang"/>
                    <field-mapping from="/harvest/OAI-PMH/ListRecords/record/metadata/oai_dc:dc/dc:source">
                        <to key="DC_SOURCE"/>
                    </field-mapping>
                    <field-mapping from="/harvest/OAI-PMH/ListRecords/record/metadata/oai_dc:dc/dc:subject">
                        <to key="DC_SUBJECT"/>
                    </field-mapping>
                    <field-mapping from="/harvest/OAI-PMH/ListRecords/record/metadata/oai_dc:dc/dc:subject@xml:lang"/>
                    <field-mapping from="/harvest/OAI-PMH/ListRecords/record/metadata/oai_dc:dc/dc:title">
                        <to key="DC_TITLE"/>
                    </field-mapping>
                    <field-mapping from="/harvest/OAI-PMH/ListRecords/record/metadata/oai_dc:dc/dc:title/dc:title"/>
                    <field-mapping from="/harvest/OAI-PMH/ListRecords/record/metadata/oai_dc:dc/dc:title@xml:lang"/>
                    <field-mapping from="/harvest/OAI-PMH/ListRecords/record/metadata/oai_dc:dc/dc:type">
                        <to typeMapping="true" key="EUROPEANA_TYPE"/>
                        <to key="DC_TYPE"/>
                    </field-mapping>
                    <!-- the table provided by BnF for normalisation has to be updated  -->
                    <field-mapping from="/harvest/OAI-PMH/ListRecords/record/metadata/oai_dc:dc/dc:type@xml:lang"/>
                    <field-mapping from="/harvest/OAI-PMH/ListRecords/resumptionToken"/>
                    <field-mapping from="/harvest/OAI-PMH/ListRecords/resumptionToken@completeListSize"/>
                    <field-mapping from="/harvest/OAI-PMH/ListRecords/resumptionToken@cursor"/>
                    <field-mapping from="/harvest/OAI-PMH/ListRecords/resumptionToken@expirationDate"/>
                    <field-mapping from="/harvest/OAI-PMH/request"/>
                    <field-mapping from="/harvest/OAI-PMH/request@from"/>
                    <field-mapping from="/harvest/OAI-PMH/request@metadataPrefix"/>
                    <field-mapping from="/harvest/OAI-PMH/request@resumptionToken"/>
                    <field-mapping from="/harvest/OAI-PMH/request@set"/>
                    <field-mapping from="/harvest/OAI-PMH/request@verb"/>
                    <field-mapping from="/harvest/OAI-PMH/responseDate"/>
                    <field-mapping from="/harvest/OAI-PMH@xsi:schemaLocation"/>
                </field-mappings>
            </source>
        </sources>
        <type-mappings>
            <type-mapping type="TEXT">
                <from>text</from>
                <from>monographie imprimée</from>
                <from>printed monograph</from>
                <from>publication en série imprimée</from>
                <from>printed serial</from>
                <from>manuscrit</from>
                <from>manuscript</from>
            </type-mapping>
            <type-mapping type="IMAGE">
                <from>image</from>
                <from>image fixe</from>
                <from>still image</from>
                <from>cartographic resource</from>
                <from>document cartographique</from>
                <from>printed cartographic resource</from>
                <from>manuscript cartographic resource</from>
                <from>document cartographique imprimé</from>
                <from>document cartographique manuscrit</from>
                <from>dessin</from>
                <from>drawing</from>
                <from>estampe</from>
                <from>engraving</from>
                <from>photographie</from>
                <from>photograph</from>
                <from>atlas</from>
                <from>diagramme</from>
                <from>diagram</from>
                <from>globe</from>
                <from>carte</from>
                <from>map</from>
                <from>maquette</from>
                <from>model</from>
                <from>image de télédétection</from>
                <from>remote sensing image</from>
                <from>coupe</from>
                <from>section</from>
                <from>vue</from>
                <from>view</from>
                <from>plan</from>
            </type-mapping>
            <type-mapping type="SOUND">
                <from>sound</from>
                <from>enregistrement sonore</from>
            </type-mapping>
            <type-mapping type="VIDEO">
                <from>image animée</from>
                <from>moving image</from>
            </type-mapping>
        </type-mappings>
    </profile>
    <profile name="04801_AA_FR_INA_local" directory="04801_AA_FR_INA_local/input_source/" publisherId="048" publisherName="">
        <sources>
            <source file="04801_AA_FR_INA.xml"
                    recordSeparator="item"
                    collectionId="04801">
                <additions>
                    <addition key="EUROPEANA_LANGUAGE" value="fr"/>
                    <addition key="EUROPEANA_COUNTRY" value="france_t"/>
                    <addition key="EUROPEANA_PROVIDER" value="Ina"/>
                </additions>
                <field-mappings>
                    <field-mapping from="/feed/item//feed/item/Bitrate"/>
                    <field-mapping from="/feed/item//feed/item/Copyright">
                        <!--<to key="DC_FROM"/>-->
                        <to key="DC_RIGHTS"/>
                    </field-mapping>
                    <field-mapping from="/feed/item/Description">
                        <to key="DC_DESCRIPTION"/>
                    </field-mapping>
                    <field-mapping from="/feed/item/DiffusionDate">
                        <to converter="YearExtractor" key="EUROPEANA_YEAR"/>
                        <to key="DC_DATE"/>
                    </field-mapping>
                    <field-mapping from="/feed/item/DiffusionTime"/>
                    <field-mapping from="/feed/item/Duration">
                        <to key="DCTERMS_EXTENT"/>
                    </field-mapping>
                    <field-mapping from="/feed/item/Framerate"/>
                    <field-mapping from="/feed/item/Keywords">
                        <to key="DC_SUBJECT"/>
                    </field-mapping>
                    <field-mapping from="/feed/item/MediaWidthHeight"/>
                    <field-mapping from="/feed/item/MimeType">
                        <to key="DC_FORMAT"/>
                    </field-mapping>
                    <field-mapping from="/feed/item/ObjectType">
                        <to typeMapping="true" key="EUROPEANA_TYPE"/>
                        <to key="DC_TYPE"/>
                    </field-mapping>
                    <field-mapping from="/feed/item/ObjectURL">
                        <to uriMapping="true" key="EUROPEANA_URI"/>
                        <to key="EUROPEANA_IS_SHOWN_BY"/>
                    </field-mapping>
                    <field-mapping from="/feed/item/PlayerURL">
                        <to key="EUROPEANA_IS_SHOWN_AT"/>
                    </field-mapping>
                    <field-mapping from="/feed/item/PlayerWidthHeight"/>
                    <field-mapping from="/feed/item/RefererURL">
                        <to key="DCTERMS_IS_PART_OF"/>
                    </field-mapping>
                    <field-mapping from="/feed/item/SubstituteThumbnailURL">
                        <to key="EUROPEANA_OBJECT"/>
                    </field-mapping>
                    <field-mapping from="/feed/item/Title">
                        <to key="DC_TITLE"/>
                    </field-mapping>
                </field-mappings>
            </source>
        </sources>
        <type-mappings>
            <type-mapping type="VIDEO">
                <from>video</from>
            </type-mapping>
        </type-mappings>
    </profile>
    <profile name="03902_Ag_FR_MCC_louvre_atlas" directory="03902_Ag_FR_MCC_louvre_atlas/input_source/" publisherId="039">
        <sources>
            <source file="03902_Ag_FR_MCC_louvre_atlas.xml"
                    recordSeparator="data"
                    collectionId="03902">
                <additions>
                    <addition key="EUROPEANA_COUNTRY" value="france_t"/>
                    <addition key="EUROPEANA_LANGUAGE" value="fr"/>
                    <addition key="EUROPEANA_PROVIDER" value="Louvre"/>
                    <addition key="EUROPEANA_TYPE" value="IMAGE"/>
                </additions>
                <field-mappings>
                    <field-mapping from="/harvest/data/oeuvre/acquisition">
                        <to key="DCTERMS_PROVENANCE"/>
                    </field-mapping>
                    <field-mapping from="/harvest/data/oeuvre/chapeau">
                        <to key="EUROPEANA_UNSTORED"/>
                    </field-mapping>
                    <field-mapping from="/harvest/data/oeuvre/complementauteur">
                        <to key="EUROPEANA_UNSTORED"/>
                    </field-mapping>
                    <field-mapping from="/harvest/data/oeuvre/date">
                        <to converter="YearExtractor" key="EUROPEANA_YEAR"/>
                        <to key="DC_DATE"/>
                    </field-mapping>
                    <field-mapping from="/harvest/data/oeuvre/dateacquisition"/>
                    <field-mapping from="/harvest/data/oeuvre/departement/couleur"/>
                    <field-mapping from="/harvest/data/oeuvre/departement/lbcourt"/>
                    <field-mapping from="/harvest/data/oeuvre/departement/lblong">
                        <to key="DC_SOURCE"/>
                    </field-mapping>
                    <field-mapping from="/harvest/data/oeuvre/departement/numordredept"/>
                    <field-mapping from="/harvest/data/oeuvre/departement@id"/>
                    <field-mapping from="/harvest/data/oeuvre/dimension">
                        <to key="DCTERMS_EXTENT"/>
                    </field-mapping>
                    <field-mapping from="/harvest/data/oeuvre/lieufabrication">
                        <to key="DCTERMS_SPATIAL"/>
                    </field-mapping>
                    <field-mapping from="/harvest/data/oeuvre/lieuprovenance">
                        <to key="DCTERMS_SPATIAL"/>
                    </field-mapping>
                    <field-mapping from="/harvest/data/oeuvre/listeauteurs/auteur/dates">
                        <to key="DC_CREATOR"/>
                    </field-mapping>
                    <!--  put in a single dc creator the "nom" followed by dates with a "coma blank" separator -->
                    <field-mapping from="/harvest/data/oeuvre/listeauteurs/auteur/identite">
                        <to key="EUROPEANA_UNSTORED"/>
                    </field-mapping>
                    <field-mapping from="/harvest/data/oeuvre/listeauteurs/auteur/nom">
                        <to key="DC_CREATOR"/>
                    </field-mapping>
                    <field-mapping from="/harvest/data/oeuvre/listeauteurs/auteur/nomdictionnaire">
                        <to key="EUROPEANA_UNSTORED"/>
                    </field-mapping>
                    <field-mapping from="/harvest/data/oeuvre/listeauteurs/auteur@id"/>
                    <field-mapping from="/harvest/data/oeuvre/listecategories/categorie">
                        <to key="DC_SUBJECT"/>
                    </field-mapping>
                    <field-mapping from="/harvest/data/oeuvre/listecategories/categorie@id"/>
                    <field-mapping from="/harvest/data/oeuvre/listeobjets/image/copyright">
                        <to key="DC_RIGHTS"/>
                    </field-mapping>
                    <field-mapping from="/harvest/data/oeuvre/listeobjets/image/descriptif"/>
                    <field-mapping from="/harvest/data/oeuvre/listeobjets/image/fgrestrictionaffichage"/>
                    <field-mapping from="/harvest/data/oeuvre/listeobjets/image/largeurobjet"/>
                    <field-mapping from="/harvest/data/oeuvre/listeobjets/image/longueurobjet"/>
                    <field-mapping from="/harvest/data/oeuvre/listeobjets/image/src">
                        <to converter="PrefixSuffix|http://cartelfr.louvre.fr/pub/fr/image/x200_| "
                            key="EUROPEANA_OBJECT"/>
                    </field-mapping>
                    <!--  to be constructed with prefix 'http://cartelfr.louvre.fr/pub/fr/image/x200_'to the value -->
                    <!-- all the records without this tag must be eliminated as they have not digitised object attached> There are only 18721 records with images out of 25769 records in this file -->
                    <!-- create europeana:type with the value 'image'for all the records having a digital image -->
                    <field-mapping from="/harvest/data/oeuvre/listeobjets/image/typeobjet"/>
                    <field-mapping from="/harvest/data/oeuvre/listeobjets/image@fgprincipal"/>
                    <field-mapping from="/harvest/data/oeuvre/listeobjets/objet/copyright"/>
                    <field-mapping from="/harvest/data/oeuvre/listeobjets/objet/descriptif"/>
                    <field-mapping from="/harvest/data/oeuvre/listeobjets/objet/fgrestrictionaffichage"/>
                    <field-mapping from="/harvest/data/oeuvre/listeobjets/objet/largeurobjet"/>
                    <field-mapping from="/harvest/data/oeuvre/listeobjets/objet/lib"/>
                    <field-mapping from="/harvest/data/oeuvre/listeobjets/objet/longueurobjet"/>
                    <field-mapping from="/harvest/data/oeuvre/listeobjets/objet/picto"/>
                    <field-mapping from="/harvest/data/oeuvre/listeobjets/objet/src"/>
                    <field-mapping from="/harvest/data/oeuvre/listeobjets/objet/typeobjet"/>
                    <field-mapping from="/harvest/data/oeuvre/localisation/aile"/>
                    <field-mapping from="/harvest/data/oeuvre/localisation/aile@id"/>
                    <field-mapping from="/harvest/data/oeuvre/localisation/niveau"/>
                    <field-mapping from="/harvest/data/oeuvre/localisation/niveau@id"/>
                    <field-mapping from="/harvest/data/oeuvre/localisation/plan"/>
                    <field-mapping from="/harvest/data/oeuvre/localisation/plan@id"/>
                    <field-mapping from="/harvest/data/oeuvre/localisation/salle/lib"/>
                    <field-mapping from="/harvest/data/oeuvre/localisation/salle/num"/>
                    <field-mapping from="/harvest/data/oeuvre/localisation/salle/precision"/>
                    <field-mapping from="/harvest/data/oeuvre/localisation/salle/vitrine"/>
                    <field-mapping from="/harvest/data/oeuvre/localisation/salle@id"/>
                    <field-mapping from="/harvest/data/oeuvre/localisation@type"/>
                    <field-mapping from="/harvest/data/oeuvre/ninvcartel">
                        <to key="DC_IDENTIFIER"/>
                    </field-mapping>
                    <field-mapping from="/harvest/data/oeuvre/sstitre">
                        <to key="DC_TITLE"/>
                    </field-mapping>
                    <!--  subtile to put in a single dc:title after "titre" with "dot blank" separator -->
                    <field-mapping from="/harvest/data/oeuvre/techniquematiere">
                        <to key="DCTERMS_MEDIUM"/>
                    </field-mapping>
                    <field-mapping from="/harvest/data/oeuvre/texte">
                        <to key="DC_DESCRIPTION"/>
                    </field-mapping>
                    <field-mapping from="/harvest/data/oeuvre/titre">
                        <to key="DC_TITLE"/>
                    </field-mapping>
                    <field-mapping from="/harvest/data/oeuvre@id">
                        <to converter="PrefixSuffix|http://cartelfr.louvre.fr/cartelfr/visite?srv=car_not_frame&amp;idNotice=| "
                            key="EUROPEANA_IS_SHOWN_BY"/>
                        <to uriMapping="true" key="EUROPEANA_URI"/>
                    </field-mapping>
                    <!-- to be constructed with the prefix 'http://cartelfr.louvre.fr/cartelfr/visite?srv=car_not_frame&idNotice=' -->
                    <field-mapping from="/harvest/data/oeuvre@langue"/>
                    <field-mapping from="/harvest/data/oeuvre@ninv"/>
                </field-mappings>
            </source>
        </sources>
        <type-mappings>
            <type-mapping type="TEXT">
                <from>text</from>
            </type-mapping>
        </type-mappings>
    </profile>
    <profile name="074_M_BE_MuseeRoyalMariemont_oai_dc" directory="074_M_BE_MuseeRoyalMariemont_oai_dc/input_source/" publisherId="074">
        <sources>
            <source file="074_M_BE_MuseeRoyalMariemont_oai_dc.xml"
                    recordSeparator="{http://www.openarchives.org/OAI/2.0/}record"
                    collectionId="074">
                <additions>
                    <addition key="EUROPEANA_COUNTRY" value="belgium"/>
                    <addition key="EUROPEANA_PROVIDER" value="Mariemont"/>
                    <addition key="EUROPEANA_TYPE" value="IMAGE"/>
                    <addition key="EUROPEANA_LANGUAGE" value="fr"/>
                </additions>
                <field-mappings>
                    <field-mapping from="/harvest/OAI-PMH/Identify/adminEmail"/>
                    <field-mapping from="/harvest/OAI-PMH/Identify/baseURL"/>
                    <field-mapping from="/harvest/OAI-PMH/Identify/deletedRecord"/>
                    <field-mapping from="/harvest/OAI-PMH/Identify/earliestDatestamp"/>
                    <field-mapping from="/harvest/OAI-PMH/Identify/granularity"/>
                    <field-mapping from="/harvest/OAI-PMH/Identify/protocolVersion"/>
                    <field-mapping from="/harvest/OAI-PMH/Identify/repositoryName"/>
                    <field-mapping from="/harvest/OAI-PMH/ListMetadataFormats/metadataFormat/metadataNamespace"/>
                    <field-mapping from="/harvest/OAI-PMH/ListMetadataFormats/metadataFormat/metadataPrefix"/>
                    <field-mapping from="/harvest/OAI-PMH/ListMetadataFormats/metadataFormat/schema"/>
                    <field-mapping from="/harvest/OAI-PMH/ListRecords/record/header/datestamp"/>
                    <field-mapping from="/harvest/OAI-PMH/ListRecords/record/header/identifier">
                        <to key="DC_IDENTIFIER"/>
                        <to uriMapping="true" key="EUROPEANA_URI"/>
                    </field-mapping>
                    <field-mapping from="/harvest/OAI-PMH/ListRecords/record/metadata/oai_dc:dc/dc:contributor">
                        <to key="DC_CONTRIBUTOR"/>
                    </field-mapping>
                    <field-mapping from="/harvest/OAI-PMH/ListRecords/record/metadata/oai_dc:dc/dc:creator">
                        <to key="DC_CREATOR"/>
                    </field-mapping>
                    <field-mapping from="/harvest/OAI-PMH/ListRecords/record/metadata/oai_dc:dc/dc:date">
                        <to converter="YearExtractor" key="EUROPEANA_YEAR"/>
                        <to key="DC_DATE"/>
                    </field-mapping>
                    <field-mapping from="/harvest/OAI-PMH/ListRecords/record/metadata/oai_dc:dc/dc:description">
                        <to key="DC_DESCRIPTION"/>
                    </field-mapping>
                    <field-mapping from="/harvest/OAI-PMH/ListRecords/record/metadata/oai_dc:dc/dc:format">
                        <to key="DC_FORMAT"/>
                    </field-mapping>
                    <field-mapping from="/harvest/OAI-PMH/ListRecords/record/metadata/oai_dc:dc/dc:identifier">
                        <to key="EUROPEANA_IS_SHOWN_BY"/>
                        <to key="EUROPEANA_OBJECT"/>
                    </field-mapping>
                    <field-mapping from="/harvest/OAI-PMH/ListRecords/record/metadata/oai_dc:dc/dc:language">
                        <to key="DC_LANGUAGE"/>
                        <to key="EUROPEANA_LANGUAGE"/>
                    </field-mapping>
                    <field-mapping from="/harvest/OAI-PMH/ListRecords/record/metadata/oai_dc:dc/dc:publisher">
                        <to key="DC_PUBLISHER"/>
                    </field-mapping>
                    <field-mapping from="/harvest/OAI-PMH/ListRecords/record/metadata/oai_dc:dc/dc:relation">
                        <to key="DC_RELATION"/>
                    </field-mapping>
                    <field-mapping from="/harvest/OAI-PMH/ListRecords/record/metadata/oai_dc:dc/dc:rights">
                        <to key="DC_RIGHTS"/>
                    </field-mapping>
                    <field-mapping from="/harvest/OAI-PMH/ListRecords/record/metadata/oai_dc:dc/dc:source">
                        <to key="DC_SOURCE"/>
                    </field-mapping>
                    <field-mapping from="/harvest/OAI-PMH/ListRecords/record/metadata/oai_dc:dc/dc:subject">
                        <to key="DC_SUBJECT"/>
                    </field-mapping>
                    <field-mapping from="/harvest/OAI-PMH/ListRecords/record/metadata/oai_dc:dc/dc:title">
                        <to key="DC_TITLE"/>
                    </field-mapping>
                    <field-mapping from="/harvest/OAI-PMH/ListRecords/record/metadata/oai_dc:dc/dc:type">
                        <to key="DC_TYPE"/>
                    </field-mapping>
                    <field-mapping from="/harvest/OAI-PMH/ListRecords/record/metadata/oai_dc:dc@xsi:schemaLocation"/>
                    <field-mapping from="/harvest/OAI-PMH/ListRecords/resumptionToken"/>
                    <field-mapping from="/harvest/OAI-PMH/ListRecords/resumptionToken@completeListSize"/>
                    <field-mapping from="/harvest/OAI-PMH/ListRecords/resumptionToken@cursor"/>
                    <field-mapping from="/harvest/OAI-PMH/error"/>
                    <field-mapping from="/harvest/OAI-PMH/error@code"/>
                    <field-mapping from="/harvest/OAI-PMH/request"/>
                    <field-mapping from="/harvest/OAI-PMH/request@metadataPrefix"/>
                    <field-mapping from="/harvest/OAI-PMH/request@resumptionToken"/>
                    <field-mapping from="/harvest/OAI-PMH/request@verb"/>
                    <field-mapping from="/harvest/OAI-PMH/responseDate"/>
                    <field-mapping from="/harvest/OAI-PMH@xsi:schemaLocation"/>
                </field-mappings>
            </source>
        </sources>
        <type-mappings>
            <type-mapping type="IMAGE">
                <from>Image fixe</from>
            </type-mapping>
        </type-mappings>
    </profile>
    <profile name="018_UK_MLA_BedesWorld_dc" directory="018_UK_MLA_BedesWorld_dc/input_source/" publisherId="018">
        <sources>
            <source file="018_UK_MLA_BedesWorld_dc.xml"
                    recordSeparator="{http://www.openarchives.org/OAI/2.0/}record"
                    collectionId="018">
                <additions>
                    <addition key="EUROPEANA_COUNTRY" value="uk"/>
                    <addition key="EUROPEANA_PROVIDER" value="MLA"/>
                    <addition key="EUROPEANA_TYPE" value="IMAGE"/>
                    <addition key="EUROPEANA_LANGUAGE" value="en"/>
                </additions>
                <field-mappings>
                    <field-mapping from="/harvest/OAI-PMH/Identify/adminEmail"/>
                    <field-mapping from="/harvest/OAI-PMH/Identify/baseURL"/>
                    <field-mapping from="/harvest/OAI-PMH/Identify/deletedRecord"/>
                    <field-mapping from="/harvest/OAI-PMH/Identify/description/oai-identifier/delimiter"/>
                    <field-mapping from="/harvest/OAI-PMH/Identify/description/oai-identifier/repositoryIdentifier"/>
                    <field-mapping from="/harvest/OAI-PMH/Identify/description/oai-identifier/sampleIdentifier"/>
                    <field-mapping from="/harvest/OAI-PMH/Identify/description/oai-identifier/scheme"/>
                    <field-mapping from="/harvest/OAI-PMH/Identify/description/oai-identifier@xsi:schemaLocation"/>
                    <field-mapping from="/harvest/OAI-PMH/Identify/granularity"/>
                    <field-mapping from="/harvest/OAI-PMH/Identify/protocolVersion"/>
                    <field-mapping from="/harvest/OAI-PMH/Identify/repositoryName"/>
                    <field-mapping from="/harvest/OAI-PMH/ListMetadataFormats/metadataFormat/metadataNamespace"/>
                    <field-mapping from="/harvest/OAI-PMH/ListMetadataFormats/metadataFormat/metadataPrefix"/>
                    <field-mapping from="/harvest/OAI-PMH/ListMetadataFormats/metadataFormat/schema"/>
                    <field-mapping from="/harvest/OAI-PMH/ListRecords/record/header/datestamp"/>
                    <!--  no URL is available, ask content provider. -->
                    <field-mapping from="/harvest/OAI-PMH/ListRecords/record/header/identifier">
                        <to key="DC_IDENTIFIER"/>
                        <to uriMapping="true" key="EUROPEANA_URI"/>
                    </field-mapping>
                    <field-mapping from="/harvest/OAI-PMH/ListRecords/record/metadata/oai_dc:dc/collection">
                        <to key="DCTERMS_IS_PART_OF"/>
                    </field-mapping>
                    <field-mapping from="/harvest/OAI-PMH/ListRecords/record/metadata/oai_dc:dc/dc:ItemType">
                        <to key="DC_TYPE"/>
                        <to typeMapping="true" key="EUROPEANA_TYPE"/>
                    </field-mapping>
                    <field-mapping from="/harvest/OAI-PMH/ListRecords/record/metadata/oai_dc:dc/dc:dateLastModified"/>
                    <field-mapping from="/harvest/OAI-PMH/ListRecords/record/metadata/oai_dc:dc/dc:description">
                        <to key="DC_DESCRIPTION"/>
                    </field-mapping>
                    <field-mapping from="/harvest/OAI-PMH/ListRecords/record/metadata/oai_dc:dc/dc:rights">
                        <to key="DC_RIGHTS"/>
                        <!--<to convertor="YearExtractor" key="EUROPEANA_YEAR"/>-->
                    </field-mapping>
                    <field-mapping from="/harvest/OAI-PMH/ListRecords/record/metadata/oai_dc:dc/dc:subject">
                        <to key="DC_SUBJECT"/>
                    </field-mapping>
                    <field-mapping from="/harvest/OAI-PMH/ListRecords/record/metadata/oai_dc:dc/dc:title">
                        <to key="DC_TITLE"/>
                    </field-mapping>
                    <field-mapping from="/harvest/OAI-PMH/ListRecords/record/metadata/oai_dc:dc@xsi:schemaLocation"/>
                    <field-mapping from="/harvest/OAI-PMH/ListRecords/resumptionToken"/>
                    <field-mapping from="/harvest/OAI-PMH/ListRecords/resumptionToken@cursor"/>
                    <field-mapping from="/harvest/OAI-PMH/ListRecords/resumptionToken@expirationDate"/>
                    <field-mapping from="/harvest/OAI-PMH/request"/>
                    <field-mapping from="/harvest/OAI-PMH/request@verb"/>
                    <field-mapping from="/harvest/OAI-PMH/responseDate"/>
                    <field-mapping from="/harvest/OAI-PMH@xsi:schemaLocation"/>
                </field-mappings>
            </source>
        </sources>
        <type-mappings>
            <type-mapping type="TEXT">
                <from>text</from>
            </type-mapping>
        </type-mappings>
    </profile>
    <profile name="04301_L_NL_NatLib_MemoryNetherlands_dcx" directory="04301_L_NL_NatLib_MemoryNetherlands_dcx/input_source/"
             publisherId="043">
        <sources>
            <source file="04301_L_NL_NatLib_MemoryNetherlands_dcx.xml"
                    recordSeparator="{http://www.openarchives.org/OAI/2.0/}record"
                    collectionId="04031">
                <additions>
                    <addition key="EUROPEANA_LANGUAGE" value="nl"/>
                    <addition key="EUROPEANA_COUNTRY" value="netherlands_t"/>
                    <addition key="EUROPEANA_PROVIDER" value="GVN"/>
                </additions>
                <field-mappings>
                    <field-mapping from="/harvest/OAI-PMH/ListRecords/record/header/datestamp"/>
                    <field-mapping from="/harvest/OAI-PMH/ListRecords/record/header/identifier"/>
                    <field-mapping from="/harvest/OAI-PMH/ListRecords/record/header@status"/>
                    <field-mapping from="/harvest/OAI-PMH/ListRecords/record/metadata/srw_dc:dc/dc:contributor">
                        <to key="DC_CONTRIBUTOR"/>
                    </field-mapping>
                    <field-mapping
                            from="/harvest/OAI-PMH/ListRecords/record/metadata/srw_dc:dc/dc:contributor@dcx:role">
                        <to key="EUROPEANA_UNSTORED"/>
                    </field-mapping>
                    <field-mapping from="/harvest/OAI-PMH/ListRecords/record/metadata/srw_dc:dc/dc:creator">
                        <to key="DC_CREATOR"/>
                    </field-mapping>
                    <field-mapping from="/harvest/OAI-PMH/ListRecords/record/metadata/srw_dc:dc/dc:creator@dcx:role">
                        <to key="EUROPEANA_UNSTORED"/>
                    </field-mapping>
                    <field-mapping from="/harvest/OAI-PMH/ListRecords/record/metadata/srw_dc:dc/dc:description">
                        <to key="DC_DESCRIPTION"/>
                    </field-mapping>
                    <field-mapping
                            from="/harvest/OAI-PMH/ListRecords/record/metadata/srw_dc:dc/dc:description@xml:lang"/>
                    <field-mapping
                            from="/harvest/OAI-PMH/ListRecords/record/metadata/srw_dc:dc/dc:description@xsi:type"/>
                    <field-mapping from="/harvest/OAI-PMH/ListRecords/record/metadata/srw_dc:dc/dc:identifier">
                        <to key="DC_IDENTIFIER"/>
                        <to key="EUROPEANA_IS_SHOWN_BY"/>
                    </field-mapping>
                    <field-mapping from="/harvest/OAI-PMH/ListRecords/record/metadata/srw_dc:dc/dc:identifier@xsi:type">
                        <to key="EUROPEANA_UNSTORED"/>
                    </field-mapping>
                    <field-mapping from="/harvest/OAI-PMH/ListRecords/record/metadata/srw_dc:dc/dc:rights">
                        <to key="DC_RIGHTS"/>
                    </field-mapping>
                    <field-mapping from="/harvest/OAI-PMH/ListRecords/record/metadata/srw_dc:dc/dc:rights@xml:lang"/>
                    <field-mapping from="/harvest/OAI-PMH/ListRecords/record/metadata/srw_dc:dc/dc:source">
                        <to key="EUROPEANA_UNSTORED"/>
                    </field-mapping>
                    <field-mapping from="/harvest/OAI-PMH/ListRecords/record/metadata/srw_dc:dc/dc:source@xsi:type"/>
                    <field-mapping from="/harvest/OAI-PMH/ListRecords/record/metadata/srw_dc:dc/dc:subject">
                        <to key="DC_SUBJECT"/>
                    </field-mapping>
                    <field-mapping from="/harvest/OAI-PMH/ListRecords/record/metadata/srw_dc:dc/dc:subject@xml:lang"/>
                    <field-mapping from="/harvest/OAI-PMH/ListRecords/record/metadata/srw_dc:dc/dc:subject@xsi:type"/>
                    <field-mapping from="/harvest/OAI-PMH/ListRecords/record/metadata/srw_dc:dc/dc:title">
                        <to key="DC_TITLE"/>
                    </field-mapping>
                    <field-mapping from="/harvest/OAI-PMH/ListRecords/record/metadata/srw_dc:dc/dc:title@xml:lang"/>
                    <field-mapping from="/harvest/OAI-PMH/ListRecords/record/metadata/srw_dc:dc/dc:type">
                        <to chooseFirst="true" typeMapping="true" key="EUROPEANA_TYPE"/>
                        <to key="DC_TYPE"/>
                    </field-mapping>
                    <field-mapping from="/harvest/OAI-PMH/ListRecords/record/metadata/srw_dc:dc/dcterms:alternative">
                        <to key="DCTERMS_ALTERNATIVE"/>
                    </field-mapping>
                    <field-mapping from="/harvest/OAI-PMH/ListRecords/record/metadata/srw_dc:dc/dcterms:created">
                        <to converter="YearExtractor" key="EUROPEANA_YEAR"/>
                        <to key="DCTERMS_CREATED"/>
                    </field-mapping>
                    <field-mapping
                            from="/harvest/OAI-PMH/ListRecords/record/metadata/srw_dc:dc/dcterms:created@xsi:type"/>
                    <field-mapping from="/harvest/OAI-PMH/ListRecords/record/metadata/srw_dc:dc/dcterms:extent">
                        <to key="DCTERMS_EXTENT"/>
                    </field-mapping>
                    <field-mapping
                            from="/harvest/OAI-PMH/ListRecords/record/metadata/srw_dc:dc/dcterms:extent@xsi:type"/>
                    <field-mapping from="/harvest/OAI-PMH/ListRecords/record/metadata/srw_dc:dc/dcterms:hasPart">
                        <to key="DCTERMS_HAS_PART"/>
                    </field-mapping>
                    <field-mapping
                            from="/harvest/OAI-PMH/ListRecords/record/metadata/srw_dc:dc/dcterms:hasPart@xsi:type"/>
                    <field-mapping from="/harvest/OAI-PMH/ListRecords/record/metadata/srw_dc:dc/dcterms:isPartOf">
                        <to key="DCTERMS_IS_PART_OF"/>
                    </field-mapping>
                    <field-mapping
                            from="/harvest/OAI-PMH/ListRecords/record/metadata/srw_dc:dc/dcterms:isPartOf@xsi:type"/>
                    <field-mapping from="/harvest/OAI-PMH/ListRecords/record/metadata/srw_dc:dc/dcterms:issued">
                        <to key="DCTERMS_ISSUED"/>
                    </field-mapping>
                    <field-mapping
                            from="/harvest/OAI-PMH/ListRecords/record/metadata/srw_dc:dc/dcterms:issued@xsi:type"/>
                    <field-mapping from="/harvest/OAI-PMH/ListRecords/record/metadata/srw_dc:dc/dcterms:medium">
                        <to key="DCTERMS_MEDIUM"/>
                    </field-mapping>
                    <field-mapping from="/harvest/OAI-PMH/ListRecords/record/metadata/srw_dc:dc/dcterms:spatial">
                        <to key="DCTERMS_SPATIAL"/>
                    </field-mapping>
                    <field-mapping
                            from="/harvest/OAI-PMH/ListRecords/record/metadata/srw_dc:dc/dcterms:spatial@xml:lang"/>
                    <field-mapping
                            from="/harvest/OAI-PMH/ListRecords/record/metadata/srw_dc:dc/dcterms:spatial@xsi:type"/>
                    <field-mapping from="/harvest/OAI-PMH/ListRecords/record/metadata/srw_dc:dc/dcterms:temporal">
                        <to key="DCTERMS_TEMPORAL"/>
                    </field-mapping>
                    <field-mapping
                            from="/harvest/OAI-PMH/ListRecords/record/metadata/srw_dc:dc/dcterms:temporal@xml:lang"/>
                    <field-mapping
                            from="/harvest/OAI-PMH/ListRecords/record/metadata/srw_dc:dc/dcterms:temporal@xsi:type"/>
                    <field-mapping from="/harvest/OAI-PMH/ListRecords/record/metadata/srw_dc:dc/dcx:annotation">
                        <to key="EUROPEANA_UNSTORED"/>
                    </field-mapping>
                    <field-mapping from="/harvest/OAI-PMH/ListRecords/record/metadata/srw_dc:dc/dcx:recordIdentifier">
                        <to key="DC_IDENTIFIER"/>
                        <to uriMapping="true" key="EUROPEANA_URI"/>
                    </field-mapping>
                    <field-mapping from="/harvest/OAI-PMH/ListRecords/record/metadata/srw_dc:dc/dcx:recordRights">
                        <to key="EUROPEANA_UNSTORED"/>
                    </field-mapping>
                    <field-mapping
                            from="/harvest/OAI-PMH/ListRecords/record/metadata/srw_dc:dc/dcx:recordRights@xml:lang"/>
                    <field-mapping from="/harvest/OAI-PMH/ListRecords/record/metadata/srw_dc:dc/dcx:thumbnail">
                        <to key="DC_IDENTIFIER"/>
                        <!--<to converter="Replace|thumbnail|image" key="EUROPEANA_OBJECT"/>-->
                        <to key="EUROPEANA_IS_SHOWN_AT"/>
                        <to key="EUROPEANA_OBJECT"/>
                    </field-mapping>
                    <field-mapping
                            from="/harvest/OAI-PMH/ListRecords/record/metadata/srw_dc:dc/dcx:thumbnail@xsi:type"/>
                    <field-mapping from="/harvest/OAI-PMH/ListRecords/record/metadata/dc:dc/marcrel:DSR">
                        <to key="EUROPEANA_UNSTORED"/>
                    </field-mapping>
                    <field-mapping from="/harvest/OAI-PMH/ListRecords/record/metadata/dc:dc/marcrel:EGR">
                        <to key="EUROPEANA_UNSTORED"/>
                    </field-mapping>
                    <field-mapping from="/harvest/OAI-PMH/ListRecords/record/metadata/dc:dc/marcrel:OTH">
                        <to key="EUROPEANA_UNSTORED"/>
                    </field-mapping>
                    <field-mapping from="/harvest/OAI-PMH/ListRecords/record/metadata/dc:dc/marcrel:PBL">
                        <to key="EUROPEANA_UNSTORED"/>
                    </field-mapping>
                    <field-mapping from="/harvest/OAI-PMH/ListRecords/record/metadata/dc:dc/marcrel:PHT">
                        <to key="EUROPEANA_UNSTORED"/>
                    </field-mapping>
                    <field-mapping from="/harvest/OAI-PMH/ListRecords/record/metadata/dc:dc/marcrel:PRT">
                        <to key="EUROPEANA_UNSTORED"/>
                    </field-mapping>
                    <field-mapping from="/harvest/OAI-PMH/ListRecords/record/metadata/index/Date">
                        <to key="DC_DATE"/>
                    </field-mapping>
                    <field-mapping from="/harvest/OAI-PMH/ListRecords/record/metadata/index/auteur">
                        <to key="EUROPEANA_UNSTORED"/>
                    </field-mapping>
                    <field-mapping from="/harvest/OAI-PMH/ListRecords/record/metadata/index/collection">
                        <to key="EUROPEANA_UNSTORED"/>
                    </field-mapping>
                    <field-mapping from="/harvest/OAI-PMH/ListRecords/record/metadata/index/collectionidentifier"/>
                    <field-mapping from="/harvest/OAI-PMH/ListRecords/record/metadata/index/contributor">
                        <to key="EUROPEANA_UNSTORED"/>
                    </field-mapping>
                    <field-mapping from="/harvest/OAI-PMH/ListRecords/record/metadata/index/creation">
                        <to key="EUROPEANA_UNSTORED"/>
                    </field-mapping>
                    <field-mapping from="/harvest/OAI-PMH/ListRecords/record/metadata/index/endyear">
                        <to key="DC_DATE"/>
                    </field-mapping>
                    <field-mapping from="/harvest/OAI-PMH/ListRecords/record/metadata/index/genre">
                        <to key="EUROPEANA_UNSTORED"/>
                    </field-mapping>
                    <field-mapping from="/harvest/OAI-PMH/ListRecords/record/metadata/index/location">
                        <to key="EUROPEANA_UNSTORED"/>
                    </field-mapping>
                    <field-mapping from="/harvest/OAI-PMH/ListRecords/record/metadata/index/period">
                        <to key="EUROPEANA_UNSTORED"/>
                    </field-mapping>
                    <field-mapping from="/harvest/OAI-PMH/ListRecords/record/metadata/index/person">
                        <to key="EUROPEANA_UNSTORED"/>
                    </field-mapping>
                    <field-mapping from="/harvest/OAI-PMH/ListRecords/record/metadata/index/source">
                        <to key="EUROPEANA_UNSTORED"/>
                    </field-mapping>
                    <field-mapping from="/harvest/OAI-PMH/ListRecords/record/metadata/index/startyear">
                        <to key="DC_DATE"/>
                    </field-mapping>
                    <field-mapping from="/harvest/OAI-PMH/ListRecords/record/metadata/index/subject">
                        <to key="EUROPEANA_UNSTORED"/>
                    </field-mapping>
                    <field-mapping from="/harvest/OAI-PMH/ListRecords/record/metadata/index/subtheme">
                        <to key="EUROPEANA_UNSTORED"/>
                    </field-mapping>
                    <field-mapping from="/harvest/OAI-PMH/ListRecords/record/metadata/index/theme">
                        <to key="EUROPEANA_UNSTORED"/>
                    </field-mapping>
                    <field-mapping from="/harvest/OAI-PMH/ListRecords/record/metadata/index/title">
                        <to key="EUROPEANA_UNSTORED"/>
                    </field-mapping>
                    <field-mapping from="/harvest/OAI-PMH/ListRecords/record/metadata/index/type">
                        <to key="EUROPEANA_UNSTORED"/>
                    </field-mapping>
                    <field-mapping from="/harvest/OAI-PMH/ListRecords/record/metadata/index/where">
                        <to key="EUROPEANA_UNSTORED"/>
                    </field-mapping>
                    <field-mapping from="/harvest/OAI-PMH/ListRecords/record/metadata/index/who">
                        <to key="EUROPEANA_UNSTORED"/>
                    </field-mapping>
                </field-mappings>
            </source>
        </sources>
        <type-mappings>
            <type-mapping type="IMAGE">
                <from>image</from>
                <from>afbeelding</from>
                <from>Onbekend</from>
            </type-mapping>
            <type-mapping type="VIDEO">
                <from>video</from>
            </type-mapping>
            <type-mapping type="TEXT">
                <from>text</from>
                <from>tekst</from>
            </type-mapping>
            <type-mapping type="SOUND">
                <from>audio</from>
            </type-mapping>
        </type-mappings>
    </profile>
    <profile name="00401_Ag_UK_Scran_oai_scran" directory="00401_Ag_UK_Scran_oai_scran/input_source/" publisherId="004">
        <sources>
            <source file="00401_Ag_UK_Scran_oai_scran.xml"
                    recordSeparator="{http://www.openarchives.org/OAI/2.0/}record"
                    collectionId="00401">
                <additions>
                    <addition key="EUROPEANA_COUNTRY" value="uk_t"/>
                    <addition key="EUROPEANA_PROVIDER" value="Scran"/>
                    <addition key="EUROPEANA_TYPE" value="IMAGE"/>
                </additions>
                <field-mappings>
                    <field-mapping from="/harvest/OAI-PMH/Identify/adminEmail"/>
                    <field-mapping from="/harvest/OAI-PMH/Identify/baseURL"/>
                    <field-mapping from="/harvest/OAI-PMH/Identify/deletedRecord"/>
                    <field-mapping from="/harvest/OAI-PMH/Identify/description/oai-identifier/delimiter"/>
                    <field-mapping from="/harvest/OAI-PMH/Identify/description/oai-identifier/repositoryIdentifier"/>
                    <field-mapping from="/harvest/OAI-PMH/Identify/description/oai-identifier/sampleIdentifier"/>
                    <field-mapping from="/harvest/OAI-PMH/Identify/description/oai-identifier/scheme"/>
                    <field-mapping from="/harvest/OAI-PMH/Identify/description/oai-identifier@xsi:schemaLocation"/>
                    <field-mapping from="/harvest/OAI-PMH/Identify/earliestDatestamp"/>
                    <field-mapping from="/harvest/OAI-PMH/Identify/granularity"/>
                    <field-mapping from="/harvest/OAI-PMH/Identify/protocolVersion"/>
                    <field-mapping from="/harvest/OAI-PMH/Identify/repositoryName"/>
                    <field-mapping from="/harvest/OAI-PMH/ListMetadataFormats/metadataFormat/metadataNamespace"/>
                    <field-mapping from="/harvest/OAI-PMH/ListMetadataFormats/metadataFormat/metadataPrefix"/>
                    <field-mapping from="/harvest/OAI-PMH/ListMetadataFormats/metadataFormat/schema"/>
                    <field-mapping from="/harvest/OAI-PMH/ListRecords/record/header/datestamp"/>
                    <field-mapping from="/harvest/OAI-PMH/ListRecords/record/header/identifier"/>
                    <field-mapping
                            from="/harvest/OAI-PMH/ListRecords/record/metadata/oai_scran:scran/scran:contributor">
                        <to key="DC_CONTRIBUTOR"/>
                    </field-mapping>
                    <field-mapping
                            from="/harvest/OAI-PMH/ListRecords/record/metadata/oai_scran:scran/scran:description_concat">
                        <to key="DC_DESCRIPTION"/>
                    </field-mapping>
                    <field-mapping
                            from="/harvest/OAI-PMH/ListRecords/record/metadata/oai_scran:scran/scran:dimensions_concat">
                        <to key="DCTERMS_EXTENT"/>
                    </field-mapping>
                    <!-- It is hard to insert YAER because it is only eariest and latest date. -->
                    <field-mapping
                            from="/harvest/OAI-PMH/ListRecords/record/metadata/oai_scran:scran/scran:earliest_date">
                        <to converter="YearExtractor" key="EUROPEANA_YEAR"/>
                        <to key="DC_DATE"/>
                    </field-mapping>
                    <field-mapping
                            from="/harvest/OAI-PMH/ListRecords/record/metadata/oai_scran:scran/scran:event_concat">
                        <to key="DC_DESCRIPTION"/>
                    </field-mapping>
                    <field-mapping from="/harvest/OAI-PMH/ListRecords/record/metadata/oai_scran:scran/scran:identifier">
                        <to key="DC_IDENTIFIER"/>
                    </field-mapping>
                    <field-mapping from="/harvest/OAI-PMH/ListRecords/record/metadata/oai_scran:scran/scran:language">
                        <to key="DC_LANGUAGE"/>
                    </field-mapping>
                    <field-mapping
                            from="/harvest/OAI-PMH/ListRecords/record/metadata/oai_scran:scran/scran:latest_date">
                        <to key="DC_DATE"/>
                    </field-mapping>
                    <field-mapping
                            from="/harvest/OAI-PMH/ListRecords/record/metadata/oai_scran:scran/scran:materials_concat">
                        <to key="DCTERMS_MEDIUM"/>
                    </field-mapping>
                    <field-mapping
                            from="/harvest/OAI-PMH/ListRecords/record/metadata/oai_scran:scran/scran:record_type">
                        <to typeMapping="true" key="EUROPEANA_TYPE"/>
                    </field-mapping>
                    <field-mapping from="/harvest/OAI-PMH/ListRecords/record/metadata/oai_scran:scran/scran:record_url">
                        <to key="EUROPEANA_IS_SHOWN_BY"/>
                        <to uriMapping="true" key="EUROPEANA_URI"/>
                    </field-mapping>
                    <field-mapping
                            from="/harvest/OAI-PMH/ListRecords/record/metadata/oai_scran:scran/scran:resource/scran:resource_copyright">
                        <to key="DC_RIGHTS"/>
                    </field-mapping>
                    <field-mapping
                            from="/harvest/OAI-PMH/ListRecords/record/metadata/oai_scran:scran/scran:resource/scran:resource_identifier">
                        <to key="DC_IDENTIFIER"/>
                    </field-mapping>
                    <field-mapping
                            from="/harvest/OAI-PMH/ListRecords/record/metadata/oai_scran:scran/scran:resource/scran:resource_licensed_duration"/>
                    <field-mapping
                            from="/harvest/OAI-PMH/ListRecords/record/metadata/oai_scran:scran/scran:resource/scran:resource_licensed_file_size"/>
                    <field-mapping
                            from="/harvest/OAI-PMH/ListRecords/record/metadata/oai_scran:scran/scran:resource/scran:resource_licensed_format">
                        <to key="DC_FORMAT"/>
                    </field-mapping>
                    <field-mapping
                            from="/harvest/OAI-PMH/ListRecords/record/metadata/oai_scran:scran/scran:resource/scran:resource_licensed_url"/>
                    <field-mapping
                            from="/harvest/OAI-PMH/ListRecords/record/metadata/oai_scran:scran/scran:resource/scran:resource_licensed_x_size"/>
                    <field-mapping
                            from="/harvest/OAI-PMH/ListRecords/record/metadata/oai_scran:scran/scran:resource/scran:resource_licensed_y_size"/>
                    <field-mapping
                            from="/harvest/OAI-PMH/ListRecords/record/metadata/oai_scran:scran/scran:resource/scran:resource_postcard_url"/>
                    <field-mapping
                            from="/harvest/OAI-PMH/ListRecords/record/metadata/oai_scran:scran/scran:resource/scran:resource_thumbnail_file_size"/>
                    <field-mapping
                            from="/harvest/OAI-PMH/ListRecords/record/metadata/oai_scran:scran/scran:resource/scran:resource_thumbnail_format"/>
                    <field-mapping
                            from="/harvest/OAI-PMH/ListRecords/record/metadata/oai_scran:scran/scran:resource/scran:resource_thumbnail_url">
                        <to key="EUROPEANA_OBJECT"/>
                    </field-mapping>
                    <field-mapping
                            from="/harvest/OAI-PMH/ListRecords/record/metadata/oai_scran:scran/scran:resource/scran:resource_thumbnail_x_size"/>
                    <field-mapping
                            from="/harvest/OAI-PMH/ListRecords/record/metadata/oai_scran:scran/scran:resource/scran:resource_thumbnail_y_size"/>
                    <field-mapping
                            from="/harvest/OAI-PMH/ListRecords/record/metadata/oai_scran:scran/scran:subject_concat">
                        <to key="DC_SUBJECT"/>
                    </field-mapping>
                    <!-- Could be dc:title, but DC website says it depends on application. -->
                    <field-mapping from="/harvest/OAI-PMH/ListRecords/record/metadata/oai_scran:scran/scran:subtitle">
                        <to key="DCTERMS_ALTERNATIVE"/>
                    </field-mapping>
                    <field-mapping from="/harvest/OAI-PMH/ListRecords/record/metadata/oai_scran:scran/scran:title">
                        <to key="DC_TITLE"/>
                    </field-mapping>
                    <!-- This is hard to map. dc:subject or dc:coverage could be, but may not be always true. -->
                    <field-mapping
                            from="/harvest/OAI-PMH/ListRecords/record/metadata/oai_scran:scran/scran:what_concat">
                        <to key="DC_SUBJECT"/>
                    </field-mapping>
                    <!-- This field contains textual dates. -->
                    <field-mapping
                            from="/harvest/OAI-PMH/ListRecords/record/metadata/oai_scran:scran/scran:when_concat">
                        <to key="DC_DATE"/>
                    </field-mapping>
                    <!-- This is hard to map. dcterms:spatial could be, but may not be always true. -->
                    <field-mapping
                            from="/harvest/OAI-PMH/ListRecords/record/metadata/oai_scran:scran/scran:where_concat">
                        <to key="DCTERMS_SPATIAL"/>
                    </field-mapping>
                    <!-- This is hard to map -->
                    <field-mapping from="/harvest/OAI-PMH/ListRecords/record/metadata/oai_scran:scran/scran:who_concat">
                        <to key="DC_CONTRIBUTOR"/>
                    </field-mapping>
                    <field-mapping
                            from="/harvest/OAI-PMH/ListRecords/record/metadata/oai_scran:scran@xsi:schemaLocation"/>
                    <field-mapping from="/harvest/OAI-PMH/ListRecords/resumptionToken"/>
                    <field-mapping from="/harvest/OAI-PMH/ListRecords/resumptionToken@cursor"/>
                    <field-mapping from="/harvest/OAI-PMH/ListRecords/resumptionToken@expirationDate"/>
                    <field-mapping from="/harvest/OAI-PMH/error"/>
                    <field-mapping from="/harvest/OAI-PMH/error@code"/>
                    <field-mapping from="/harvest/OAI-PMH/request"/>
                    <field-mapping from="/harvest/OAI-PMH/request@metadataPrefix"/>
                    <field-mapping from="/harvest/OAI-PMH/request@resumptionToken"/>
                    <field-mapping from="/harvest/OAI-PMH/request@verb"/>
                    <field-mapping from="/harvest/OAI-PMH/responseDate"/>
                    <field-mapping from="/harvest/OAI-PMH@xsi:schemaLocation"/>
                </field-mappings>
            </source>
        </sources>
        <type-mappings>
            <type-mapping type="IMAGE">
                <from>caption</from>
                <from>collection</from>
            </type-mapping>
        </type-mappings>
    </profile>
</profiles>